


{
  "subject": "Business Studies",
  "topics": [
    {
      "title": "Types of Businesses",
      "subsections": [
        {
          "title": "Definition",
          "content": "Businesses are classified by ownership and size.",
          "points": [
            "Sole trader: Owned and operated by one person.",
            "Partnership: Business owned by 2–20 people.",
            "Corporation: Owned by shareholders; managed by directors.",
            "Cooperatives: Owned and controlled by members for mutual benefit."
          ]
        },
        {
          "title": "Advantages and Disadvantages",
          "content": "Each business type has its own strengths and weaknesses.",
          "points": [
            "Sole trader: Easy to start, but unlimited liability.",
            "Partnership: Shared responsibilities, but conflicts may arise.",
            "Corporation: Limited liability, but complex setup.",
            "Cooperative: Member-focused, but slower decision-making."
          ]
        }
      ]
    },

    {
  "title": "Business Skills for Life Skills",
  "subsections": [
    {
      "title": "Definition",
      "content": "Business skills are practical abilities that help individuals start, manage, and grow business ventures, contributing to personal development and economic empowerment.",
      "points": [
        "Enable individuals to make informed financial and operational decisions.",
        "Support entrepreneurship and self-reliance.",
        "Enhance problem-solving and communication abilities."
      ]
    },
    {
      "title": "Essential Business Skills",
      "content": "Key business skills important for life skills development include:",
      "points": [
        "Financial Literacy: Understanding money management, budgeting, and accounting.",
        "Marketing: Knowing how to promote products or services effectively.",
        "Customer Service: Building positive relationships and meeting customer needs.",
        "Planning and Organization: Setting goals, managing time, and coordinating resources.",
        "Problem-Solving: Identifying challenges and finding practical solutions.",
        "Communication: Conveying ideas clearly to customers, employees, and partners."
      ]
    },
    {
      "title": "Importance of Business Skills in Life Skills",
      "content": "Business skills empower individuals to achieve economic independence and improve quality of life.",
      "points": [
        "Encourages entrepreneurship and job creation.",
        "Helps manage personal and family finances better.",
        "Fosters confidence and decision-making abilities.",
        "Promotes critical thinking and adaptability in various life situations."
      ]
    },
    {
      "title": "Developing Business Skills",
      "content": "Business skills can be developed through education, practice, and experience.",
      "points": [
        "Participate in training workshops and courses.",
        "Engage in small business ventures or simulations.",
        "Seek mentorship from experienced entrepreneurs.",
        "Practice budgeting, planning, and marketing in daily activities."
      ]
    },
    {
      "title": "Challenges in Acquiring Business Skills",
      "content": "Several factors may hinder the development of business skills.",
      "points": [
        "Limited access to quality education and training.",
        "Lack of practical experience opportunities.",
        "Financial constraints to start or run businesses.",
        "Fear of failure and lack of confidence."
      ]
    }
  ]
},


    {
      "title": "Entrepreneurship",
      "subsections": [
        {
          "title": "Definition",
          "content": "Entrepreneurship involves starting and running a business.",
          "points": [
            "Entrepreneurs identify business opportunities.",
            "They combine resources to produce goods or services."
          ]
        },
        {
          "title": "Qualities of an Entrepreneur",
          "content": "Successful entrepreneurs share common traits.",
          "points": [
            "Creativity and innovation.",
            "Willingness to take risks.",
            "Strong leadership and decision-making skills.",
            "Persistence and self-motivation."
          ]
        },
        {
          "title": "Stages in Entrepreneurship",
          "content": "The process of turning an idea into a functioning business.",
          "points": [
            "Idea generation.",
            "Business planning.",
            "Sourcing capital.",
            "Implementation and management."
          ]
        }
      ]
    },
    {
      "title": "Marketing",
      "subsections": [
        {
          "title": "Definition",
          "content": "Marketing is promoting and selling products to customers.",
          "points": [
            "It involves understanding customer needs and delivering value."
          ]
        },
        {
          "title": "The 4 Ps of Marketing",
          "content": "Also known as the Marketing Mix.",
          "points": [
            "Product: The item or service offered.",
            "Price: The cost to the customer.",
            "Place: Where and how the product is sold.",
            "Promotion: Methods used to inform and persuade customers."
          ]
        },
        {
          "title": "Importance of Marketing",
          "content": "Effective marketing helps businesses grow and compete.",
          "points": [
            "Attracts new customers.",
            "Builds brand awareness.",
            "Increases sales and revenue."
          ]
        }
      ]
    }
  ]
}

